{"cameraMode":{"drawMode":0,"name":"Shaded","section":"Shading Mode"},"sceneLighting":false,"audioPlay":false,"sceneViewState":{"m_AlwaysRefresh":false,"showFog":true,"showSkybox":true,"showFlares":true,"showImageEffects":true,"showParticleSystems":true,"showVisualEffectGraphs":true,"m_FxEnabled":true},"in2DMode":false,"pivot":{"x":-68.95142364501953,"y":-72.4266128540039,"z":-73.07492065429688},"rotation":{"x":0.22287055850028993,"y":-0.1623057872056961,"z":0.03766042739152908,"w":0.9605064392089844},"size":159.5955047607422,"orthographic":false}